Workbook

Sheet Summary
B1: SECTION 1 - Part1 Inputs
B2: RISK FREE RATE | C2: 5.04%
B3: 10- yr AGB Justification | C3: Matches long duration equity horizon
B4: Market risk premium | C4: 0.06
B5: Levered beta | C5: 1.2384
B6: Beta method | C6: SLOPE + Covariance/Variance
B7: D/E ratio | C7: 2.88
B8: Tax Rate | C8: 0.3
B9: Unlevered beta | C9: 0.416
B12: SECTION 2 - Peer Betas
B13: COMPANY | C13: LEVERED BETA | D13: D/E | E13: TAX RATE | F13: UNLEVERED BETA
B14: WBC.AX | C14: 1.1302012 | D14: 2.91 | E14: 0.3 | F14: 0.37214396
B16: ANZ.AX | C16: 0.94592552 | D16: 3.09 | E16: 0.3 | F16: 0.2990596
B18: NAB.AX | C18: 1.3292537 | D18: 4.82 | E18: 0.3 | F18: 0.30389888
B20: MQG.AX | C20: 1.4516578 | D20: 4.88 | E20: 0.3 | F20: 0.32872687
B22: BEN.AX | C22: 1.3885924 | D22: 1.43 | E22: 0.3 | F22: 0.69394922
B24: Average | F24: 0.3995557
B26: Section 3 - DDM Inputs
B27: Label | C27: Values
B28: High Growth Rate (g1) | C28: 0.0719
B29: Stable Growth rate (g2) | C29: 0.02225
B30: Last dividend (FY2025) | C30: 4.95
B31: Ke Approach 1 | C31: 0.1247
B32: Ke Approach 2 | C32: 0.1227
B34: Section 4 - DDM results
B35: Label | C35: Approach 1 | D35: Approach 2
B36: PV of Dividends (Yr 1–5) | C36: 21.48 | D36: 21.59
B37: Terminal Value | C37: 69.91 | D37: 71.3
B38: PV of Terminal Value | C38: 38.85 | D38: 39.98
B39: Intrinsic value | C39: 60.33 | D39: 61.57
B40: Market Price | C40: 174.49 | D40: 174.49
B41: Over/undervaluation | C41: -0.6543 | D41: -0.6472
B44: Section 5 - Recommendation
B45: Valuation range | C45: $60.33-$61.57
B46: Market Price | C46: 174.49 | D46: As of 8/5/2025
B47: Verdict | C47: Overvalued (both approaches)
B48: Recommendation | C48: HOLD/AVOID

Sheet CBA.AX monthly cl prices(60mts)
A1: DATE | B1: Open | C1: High | D1: Low | E1: Close | F1: Adj Close | G1: Volume
A2: Apr 24, 2026 | B2: 174 | C2: 174.77 | D2: 171.43 | E2: 174.49 | F2: 174.49 | G2: 1680535
A3: Apr 1, 2026 | B3: 168.94 | C3: 185.59 | D3: 168.12 | E3: 174.49 | F3: 174.49 | G3: 29878847
A4: Mar 1, 2026 | B4: 173.5 | C4: 179.56 | D4: 165.09 | E4: 167.7 | F4: 167.7 | G4: 47037312
A5: Feb 1, 2026 | B5: 152.67 | C5: 180.6 | D5: 149.81 | E5: 174.62 | F5: 172.32 | G5: 50907149
A6: Jan 1, 2026 | B6: 160.57 | C6: 161.67 | D6: 146.98 | E6: 149.36 | F6: 147.39 | G6: 30942306
A7: Dec 1, 2025 | B7: 152.2 | C7: 163.1 | D7: 150.38 | E7: 160.57 | F7: 158.45 | G7: 35224722
A8: Nov 1, 2025 | B8: 170.95 | C8: 179.15 | D8: 150.48 | E8: 152.51 | F8: 150.5 | G8: 49133824
A9: Oct 1, 2025 | B9: 166.52 | C9: 175.86 | D9: 161.82 | E9: 171.64 | F9: 169.37 | G9: 38348213
A10: Sep 1, 2025 | B10: 170.58 | C10: 171.7 | D10: 162.54 | E10: 166.9 | F10: 164.7 | G10: 38572991
A11: Aug 1, 2025 | B11: 176 | C11: 180 | D11: 165.24 | E11: 170.3 | F11: 165.5 | G11: 43334823 | L11: CBA.AX monthly cl prices (60 months)
A12: Jul 1, 2025 | B12: 184.21 | C12: 184.31 | D12: 170.67 | E12: 177.91 | F12: 172.89 | G12: 43290191
A13: Jun 1, 2025 | B13: 175.9 | C13: 192 | D13: 175.2 | E13: 184.75 | F13: 179.54 | G13: 41684888
A14: May 1, 2025 | B14: 166.57 | C14: 176.64 | D14: 164.1 | E14: 175.95 | F14: 170.99 | G14: 45119064
A15: Apr 1, 2025 | B15: 151.01 | C15: 168.7 | D15: 140.21 | E15: 166.6 | F15: 161.9 | G15: 53648758
A16: Mar 1, 2025 | B16: 158.4 | C16: 158.4 | D16: 141.41 | E16: 150.93 | F16: 146.67 | G16: 48323852
A17: Feb 1, 2025 | B17: 156.5 | C17: 167.92 | D17: 148.98 | E17: 156.74 | F17: 150.21 | G17: 44666898
A18: Jan 1, 2025 | B18: 153.25 | C18: 161.7 | D18: 151 | E18: 160.56 | F18: 153.87 | G18: 32999064
A19: Dec 1, 2024 | B19: 159.5 | C19: 161.37 | D19: 150.26 | E19: 153.25 | F19: 146.87 | G19: 36875992
A20: Nov 1, 2024 | B20: 141.65 | C20: 160.27 | D20: 140.4 | E20: 158.58 | F20: 151.98 | G20: 42309266
A21: Oct 1, 2024 | B21: 135 | C21: 144.48 | D21: 132.1 | E21: 142.75 | F21: 136.8 | G21: 38198442
A22: Sep 1, 2024 | B22: 139.35 | C22: 145.24 | D22: 133 | E22: 135.39 | F22: 129.75 | G22: 52394635
A23: Aug 1, 2024 | B23: 138.21 | C23: 141.34 | D23: 124.89 | E23: 139.5 | F23: 131.3 | G23: 51323051
... A62: May 1, 2021 | B62: 89.47 | C62: 101.5 | D62: 89.21 | E62: 99.72 | F62: 83.14 | G62: 53825305

Sheet ASX 200 Monthly data
A1: Date | B1: Open | C1: High | D1: Low | E1: Close | F1: Adj Close | G1: Volume
A2: 46113 | B2: 8481.8 | C2: 9021.5 | D2: 8481.8 | E2: 8786.5 | F2: 8786.5 | G2: 12006900
A3: 46082 | B3: 9200.9 | C3: 9200.9 | D3: 8262.4 | E3: 8481.8 | F3: 8481.8 | G3: 18254900
A4: 46054 | B4: 8869.1 | C4: 9202.9 | D4: 8683.7 | E4: 9198.6 | F4: 9198.6 | G4: 14130400
A5: 46023 | B5: 8714.3 | C5: 8978.5 | D5: 8682.8 | E5: 8869.1 | F5: 8869.1 | G5: 11146900
A6: 45992 | B6: 8614.1 | C6: 8805.5 | D6: 8547.1 | E6: 8714.3 | F6: 8714.3 | G6: 13136500
A7: 45962 | B7: 8881.9 | C7: 8894.8 | D7: 8383.2 | E7: 8614.1 | F7: 8614.1 | G7: 11974800
A8: 45931 | B8: 8848.8 | C8: 9115.2 | D8: 8809 | E8: 8881.9 | F8: 8881.9 | G8: 15555200
A9: 45901 | B9: 8973.1 | C9: 8973.1 | D9: 8731.3 | E9: 8848.8 | F9: 8848.8 | G9: 17242700
A10: 45870 | B10: 8742.8 | C10: 9054.5 | D10: 8630.9 | E10: 8973.1 | F10: 8973.1 | G10: 15145500
A11: 45839 | B11: 8542.3 | C11: 8776.4 | D11: 8531.4 | E11: 8742.8 | F11: 8742.8 | G11: 14678800 | L11: ASX 200 Monthly data
A12: 45809 | B12: 8434.7 | C12: 8639.1 | D12: 8401.1 | E12: 8542.3 | F12: 8542.3 | G12: 15624700
A13: 45778 | B13: 8126.2 | C13: 8453 | D13: 8109.7 | E13: 8434.7 | F13: 8434.7 | G13: 16637500
A14: 45748 | B14: 7843.4 | C14: 8126.2 | D14: 7169.2 | E14: 8126.2 | F14: 8126.2 | G14: 15770900
A15: 45717 | B15: 8172.4 | C15: 8251.9 | D15: 7733.5 | E15: 7843.4 | F15: 7843.4 | G15: 17221100
A16: 45689 | B16: 8532.3 | C16: 8615.2 | D16: 8155.5 | E16: 8172.4 | F16: 8172.4 | G16: 14171000
A17: 45658 | B17: 8159.1 | C17: 8566.9 | D17: 8146.6 | E17: 8532.3 | F17: 8532.3 | G17: 9036500
A18: 45627 | B18: 8436.2 | C18: 8514.5 | D18: 8051.2 | E18: 8159.1 | F18: 8159.1 | G18: 11145300
A19: 45597 | B19: 8160 | C19: 8477.1 | D19: 8063.2 | E19: 8436.2 | F19: 8436.2 | G19: 11439000
A20: 45566 | B20: 8269.8 | C20: 8384.5 | D20: 8107.6 | E20: 8160 | F20: 8160 | G20: 13307400
A21: 45536 | B21: 8091.8 | C21: 8285.7 | D21: 7918.9 | E21: 8269.8 | F21: 8269.8 | G21: 15045900
A22: 45505 | B22: 8092.3 | C22: 8148.7 | D22: 7628.1 | E22: 8091.9 | F22: 8091.9 | G22: 15032500
A23: 45474 | B23: 7767.5 | C23: 8092.3 | D23: 7702.5 | E23: 8092.3 | F23: 8092.3 | G23: 12789300
... A61: 44317 | B61: 7022 | C61: 7203.3 | D61: 6917.3 | E61: 7161.6 | F61: 7161.6 | G61: 12443000

Sheet CBA TAX RATE
A1: CBA TAX RATE
A2: FINANCIAL YEAR | B2: INTERIM | C2: FINAL | D2: Total annual DPS
A3: Effective tax rate | B3: 0.305
D5: =B5+C5 -> 0
A6: FY2021 | B6: 1.75 | C6: 2 | D6: =B6+C6 -> 3.75
A7: FY2022 | B7: 2.1 | C7: 2.1 | D7: =B7+C7 -> 4.2
A8: FY2023 | B8: 2.15 | C8: 2.4 | D8: =B8+C8 -> 4.55
A9: FY2024 | B9: 2.25 | C9: 2.5 | D9: =B9+C9 -> 4.75
A10: FY2025 | B10: 2.35 | C10: 2.6 | D10: =B10+C10 -> 4.95

Sheet Real GDP growth 
A1: YEAR | B1: Yearly growth
A2: 44348 | B2: 10.2
A3: 44713 | B3: 3.8
A4: 45078 | B4: 2.3
A5: 45444 | B5: 0.9
A6: 45809 | B6: 1.9
A8: STABLE LONG-RUN GROWTH RATE | B8: =(B3+B4+B5+B6)/4 -> 2.225 | C8: > EXCLUDED Year 2021 DUE TO COVID DISTORTION
A15: REAL GDP GROWTH

Sheet CBA Target Capital st
A1: D/E ratio | B1: 2.88
A2: Tax Rate | B2: 0.3
A3: Source | B3: CBA FY2025 Annual report
A7: Currrent Share Price | B7: 174.49

Sheet (BOND YIELDS & RISK FREE RATE
A1: Q1(a) - Australian Government Bond Yield Curve
A3: MATURITY | B3: YIELD(% p.a.)
A4: 1-Year | B4: 4.704
A5: 2-Year | B5: 4.727
A6: 3-Year | B6: 4.715
A7: 5-Year | B7: 4.734
A8: 10-Year | B8: 5.036
A9: 15-Year | B9: 5.234
A10: Selected Risk-Free Rate | B10: =B8 -> 5.036
A11: Maturity selected | B11: 10-year
A12: Justification | B12: Matches long-duration equity investment horizon
H19: AUSTRALIAN GOVERNMENT BOND YIELD CURVE

Sheet BETA EST. FROM PRICE DATA
A1: Column1 | B1: Column2 | C1: Column3 | D1: Column4 | E1: Column5
A2: Date | B2: CBA PRICE ($) | C2: ASX 200 PRICE | D2: CBA RETURN | E2: ASX200 RETURN
A3: 44317 | B3: 83.14 | C3: 7161.6
A4: 44348 | B4: 83.26 | C4: 7313 | D4: =LN(B4/B3) -> 0.0014423079 | E4: =LN(C4/C3) -> 0.020920167
A5: 44378 | B5: 83.08 | C5: 7392.6 | D5: =LN(B5/B4) -> -0.0021642428 | E5: =LN(C5/C4) -> 0.010825914
A6: 44409 | B6: 83.47 | C6: 7534.9 | D6: =LN(B6/B5) -> 0.0046832869 | E6: =LN(C6/C5) -> 0.019066061
A7: 44440 | B7: 88.71 | C7: 7332.2 | D7: =LN(B7/B6) -> 0.060885337 | E7: =LN(C7/C6) -> -0.027269953
A8: 44470 | B8: 89.01 | C8: 7323.7 | D8: =LN(B8/B7) -> 0.0033761004 | E8: =LN(C8/C7) -> -0.0011599425
A9: 44501 | B9: 79.23 | C9: 7256 | D9: =LN(B9/B8) -> -0.11639371 | E9: =LN(C9/C8) -> -0.0092869519
A10: 44531 | B10: 85.88 | C10: 7444.6 | D10: =LN(B10/B9) -> 0.080595958 | E10: =LN(C10/C9) -> 0.025660225
A11: 44562 | B11: 79.71 | C11: 6971.6 | D11: =LN(B11/B10) -> -0.074555925 | E11: =LN(C11/C10) -> -0.065644184
A12: 44593 | B12: 79.47 | C12: 7049.1 | D12: =LN(B12/B11) -> -0.0030154565 | E12: =LN(C12/C11) -> 0.011055195
A13: 44621 | B13: 91.54 | C13: 7499.6 | D13: =LN(B13/B12) -> 0.14139644 | E13: =LN(C13/C12) -> 0.061949737
A14: 44652 | B14: 89.91 | C14: 7435 | D14: =LN(B14/B13) -> -0.017966865 | E14: =LN(C14/C13) -> -0.0086511059
A15: 44682 | B15: 90.32 | C15: 7211.2 | D15: =LN(B15/B14) -> 0.0045497498 | E15: =LN(C15/C14) -> -0.030563207
... A62: 46113 | B62: 174.49 | C62: 8786.5 | D62: =LN(B62/B61) -> 0.039690765 | E62: =LN(C62/C61) -> 0.035293761
B64: LEVERED BETA | C64: =SLOPE(D4:D62,E4:E62) -> 1.2384389
B65: COVARIANCE METHOD | C65: =_xlfn.COVARIANCE.S(D4:D62,E4:E62)/_xlfn.VAR.S(E4:E62) -> 1.2384389
B68: Debt-to-Equity Ratio(D/E) | C68: 2.88
B69: Corporate Tax Rate | C69: 0.3
B70: Source | C70: CBA FY2025 Annual report
B72: Unlevered Beta | C72: =C65/(1+(1-C69)*C68) -> 0.41062299

Sheet Peer Return Sheet
A1: DATE | B1: WBC Price | C1: WBC Return | D1: ANZ Price | E1: ANZ Return | F1: NAB Price | G1: NAB Return | H1: MQG Price | I1: MQG Return | J1: BEN Price | K1: BEN return
A2: 44317 | B2: 26.278 | D2: 28.483 | F2: 26.95 | H2: 151.93 | J2: 10.35
A3: 44348 | B3: 25.671 | C3: =LN(B3/B2) -> -0.023370137 | D3: 27.928 | E3: =LN(D3/D2) -> -0.019677648 | F3: 26.22 | G3: =LN(F3/F2) -> -0.027460819 | H3: 156.43 | I3: =LN(H3/H2) -> 0.029188737 | J3: 10.49 | K3: =LN(J3/J2) -> 0.013435903
A4: 44378 | B4: 24.388 | C4: =LN(B4/B3) -> -0.051270742 | D4: 27.491 | E4: =LN(D4/D3) -> -0.015771091 | F4: 25.93 | G4: =LN(F4/F3) -> -0.011121879 | H4: 156.9 | I4: =LN(H4/H3) -> 0.0030000342 | J4: 10.33 | K4: =LN(J4/J3) -> -0.015370139
A5: 44409 | B5: 25.681 | C5: =LN(B5/B4) -> 0.051660211 | D5: 27.63 | E5: =LN(D5/D4) -> 0.0050434606 | F5: 27.73 | G5: =LN(F5/F4) -> 0.06711426 | H5: 166.74 | I5: =LN(H5/H4) -> 0.060827053 | J5: 10.04 | K5: =LN(J5/J4) -> -0.028475169
A6: 44440 | B6: 25.86 | C6: =LN(B6/B5) -> 0.0069459545 | D6: 27.928 | E6: =LN(D6/D5) -> 0.010727631 | F6: 27.83 | G6: =LN(F6/F5) -> 0.0035997159 | H6: 182 | I6: =LN(H6/H5) -> 0.087570974 | J6: 9.45 | K6: =LN(J6/J5) -> -0.060562373
A7: 44470 | B7: 25.532 | C7: =LN(B7/B6) -> -0.012764806 | D7: 27.918 | E7: =LN(D7/D6) -> -0.00035812771 | F7: 28.71 | G7: =LN(F7/F6) -> 0.031130919 | H7: 197.83 | I7: =LN(H7/H6) -> 0.083401389 | J7: 9.25 | K7: =LN(J7/J6) -> -0.02139119
A8: 44501 | B8: 20.41 | C8: =LN(B8/B7) -> -0.22390759 | D8: 26.489 | E8: =LN(D8/D7) -> -0.05254209 | F8: 27.3 | G8: =LN(F8/F7) -> -0.050358792 | H8: 196.74 | I8: =LN(H8/H7) -> -0.005525016 | J8: 8.57 | K8: =LN(J8/J7) -> -0.076355819
A9: 44531 | B9: 21.235 | C9: =LN(B9/B8) -> 0.039625787 | D9: 27.293 | E9: =LN(D9/D8) -> 0.029900707 | F9: 28.84 | G9: =LN(F9/F8) -> 0.05487661 | H9: 205.4 | I9: =LN(H9/H8) -> 0.043076237 | J9: 9.1 | K9: =LN(J9/J8) -> 0.060006681
A10: 44562 | B10: 20.191 | C10: =LN(B10/B9) -> -0.050413803 | D10: 26.32 | E10: =LN(D10/D9) -> -0.036301153 | F10: 27.13 | G10: =LN(F10/F9) -> -0.061123186 | H10: 183.62 | I10: =LN(H10/H9) -> -0.11209089 | J10: 8.58 | K10: =LN(J10/J9) -> -0.0588405
A11: 44593 | B11: 22.687 | C11: =LN(B11/B10) -> 0.11655511 | D11: 25.805 | E11: =LN(D11/D10) -> -0.019760835 | F11: 28.94 | G11: =LN(F11/F10) -> 0.064584595 | H11: 180.78 | I11: =LN(H11/H10) -> -0.015587582 | J11: 9.61 | K11: =LN(J11/J10) -> 0.11337031
A12: 44621 | B12: 24.11 | C12: =LN(B12/B11) -> 0.060834619 | D12: 27.382 | E12: =LN(D12/D11) -> 0.059317592 | F12: 32.35 | G12: =LN(F12/F11) -> 0.1113893 | H12: 203.27 | I12: =LN(H12/H11) -> 0.11725432 | J12: 10.29 | K12: =LN(J12/J11) -> 0.068368327
A13: 44652 | B13: 23.742 | C13: =LN(B13/B12) -> -0.015381061 | D13: 27.084 | E13: =LN(D13/D12) -> -0.010942716 | F13: 32.63 | G13: =LN(F13/F12) -> 0.0086180897 | H13: 206.98 | I13: =LN(H13/H12) -> 0.018087026 | J13: 10.65 | K13: =LN(J13/J12) -> 0.034387342
A14: 44682 | B14: 23.742 | C14: =LN(B14/B13) -> 0 | D14: 24.842 | E14: =LN(D14/D13) -> -0.086407379 | F14: 31.26 | G14: =LN(F14/F13) -> -0.042892786 | H14: 185.98 | I14: =LN(H14/H13) -> -0.10698303 | J14: 10.42 | K14: =LN(J14/J13) -> -0.021832856
... A61: 46113 | B61: 38.5 | C61: =LN(B61/B60) -> -0.024882648 | D61: 36.65 | E61: =LN(D61/D60) -> 0.018728171 | F61: 39.88 | G61: =LN(F61/F60) -> -0.038371653 | H61: 235.08 | I61: =LN(H61/H60) -> 0.15200478 | J61: 10.69 | K61: =LN(J61/J60) -> 0.077784579

Sheet Peer Betas
A1: COMPANY | B1: LEVERED BETA | C1: D/E | D1: TAX RATE | E1: UNLEVERED BETA
A2: WBC.AX | B2: =SLOPE('Peer Return Sheet'!C3:C61,'BETA EST. FROM PRICE DATA'!E4:E62) -> 1.1302012 | C2: 2.91 | D2: 0.3 | E2: =B2/(1+(1-D2)*C2) -> 0.37214396
A4: ANZ.AX | B4: =SLOPE('Peer Return Sheet'!E3:E61,'BETA EST. FROM PRICE DATA'!E4:E62) -> 0.94592552 | C4: 3.09 | D4: 0.3 | E4: =B4/(1+(1-D4)*C4) -> 0.2990596
A6: NAB.AX | B6: =SLOPE('Peer Return Sheet'!G3:G61,'BETA EST. FROM PRICE DATA'!E4:E62) -> 1.3292537 | C6: 4.82 | D6: 0.3 | E6: =B6/(1+(1-D6)*C6) -> 0.30389888
A8: MQG.AX | B8: =SLOPE('Peer Return Sheet'!I3:I61,'BETA EST. FROM PRICE DATA'!E4:E62) -> 1.4516578 | C8: 4.88 | D8: 0.3 | E8: =B8/(1+(1-D8)*C8) -> 0.32872687
A10: BEN.AX | B10: =SLOPE('Peer Return Sheet'!K3:K61,'BETA EST. FROM PRICE DATA'!E4:E62) -> 1.3885924 | C10: 1.43 | D10: 0.3 | E10: =B10/(1+(1-D10)*C10) -> 0.69394922
A12: Average | E12: =+AVERAGE(Table35[UNLEVERED BETA]) -> 0.3995557
A13: CBA D/E RATIO | B13: 2.88
A14: CBA TAX RATE | B14: 0.3
A15: INDUSTRY AVG UNLEVERED BETA | B15: =E12 -> 0.3995557
A16: RELEVERED BETA APPROACH | B16: =E12*(1+(1-B14)*B13) -> 1.20506
A17: CBA LEVERED BETA | B17: 1.2384389
A18: CBA UNLEVERED BETA | B18: 0.41062299

Sheet DDM
A1: RISK-FREE RATE | B1: 0.05036
A2: MARKET RISK PREMIUM | B2: 0.06
A3: Levered Beta (Approach 1) | B3: ='BETA EST. FROM PRICE DATA'!C64 -> 1.2384389
A4: Relevered beta (Approach 2) | B4: ='Peer Betas'!B16 -> 1.20506
A5: High Growth Rate (g1) | B5: =DDM!B8 -> 0.071873374
A6: Stable Growth rate (g2) | B6: 0.02225
A7: Last dividend (FY2025) | B7: 4.95
A8: High Growth Rate | B8: =('CBA TAX RATE'!D10/'CBA TAX RATE'!D6)^(1/4)-1 -> 0.071873374 | C8: calculation for high growth
A9: Calculating CAPM Cost of Equity
A11: Ke - Approach 1 (Firm Beta) | B11: =B1+B3*B2 -> 0.12466634
A12: Ke - Approach 2 (industry beta) | B12: =B1+B4*B2 -> 0.1226636
A14: PV of Dividends Approach 1 | H14: PV of dividends approach 2
A15: YEAR | B15: Dividend ($) | C15: PV of Dividend | H15: YEAR | I15: Dividend($) | J15: PV of Dividend
A16: 1 | B16: =B7*(1+B5) -> 5.3057732 | C16: =B16/(1+B11)^A16 -> 4.717642 | H16: 1 | I16: =B7*(1+B5) -> 5.3057732 | J16: =I16/(1+B12)^H16 -> 4.7260579
A17: 2 | B17: =B16*(1+B5) -> 5.687117 | C17: =B17/(1+B11)^(A17) -> 4.4961912 | H17: 2 | I17: =I16*(1+B5) -> 5.687117 | J17: =I17/(1+B12)^H17 -> 4.5122472
A18: 3 | B18: =B17*(1+B5) -> 6.0958693 | C18: =B18/(1+B11)^(A18) -> 4.2851355 | H18: 3 | I18: =I17*(1+B5) -> 6.0958693 | J18: =I18/(1+B12)^H18 -> 4.3081094
A19: 4 | B19: =B18*(1+B5) -> 6.534 | C19: =B19/(1+B11)^A19 -> 4.083987 | H19: 4 | I19: =I18*(1+B5) -> 6.534 | J19: =I19/(1+B12)^H19 -> 4.113207
A20: 5 | B20: =B19*(1+B5) -> 7.0036206 | C20: =B20/(1+B11)^(A20) -> 3.8922805 | H20: 5 | I20: =I19*(1+B5) -> 7.0036206 | J20: =I20/(1+B12)^H20 -> 3.9271221
A22: YEAR 6 Dividend | B22: =B20*(1+B6) -> 7.1594512
A23: Terminal Value (At Year 5) | B23: =B22/(B11-B6) -> 69.905363
A24: PV of Terminal Value | B24: =B23/(1+B11)^5 -> 38.850089
A26: Sum of PV Dividends | B26: =SUM(Table7[PV of Dividend]) -> 21.475236
A27: PV of Terminal value | B27: =B24 -> 38.850089
A28: Intrinsic Value (App1) | B28: =B26+B27 -> 60.325325
A29: Current Market Price | B29: 174.49
A30: Over/Undervaluation | B30: =(B28-B29)/B29 -> -0.65427632
A32: Year 6 dividend (App 2) | B32: =I20*(1+B6) -> 7.1594512
A33: Terminal Value (App 2) | B33: =B32/(B12-B6) -> 71.299616
A34: PV of Terminal Value (App 2) | B34: =B33/(1+B12)^5 -> 39.97965
A36: Sum of PV dividends (App 2) | B36: =SUM(J16:J20) -> 21.586744
A37: PV of Terminal Value | B37: =B34 -> 39.97965
A38: Intrinsic Value (App2) | B38: =B36+B37 -> 61.566393
A39: Over/Undervaluation(App2) | B39: =(B38-B29)/B29 -> -0.64716377

Sheet Sensitivity_
A1: TABLE 1: Intrinsic Value Sensitivity - Stable Growth Rate (g2) vs High Growth Rate (g1)
A2: Approach 1 | Ke = 12.47% | Last Dividend = $4.95 | Base intrinsic value = $60.33
A3: ↕ | B3: g2 \ g1 | C3: ← HIGH GROWTH RATE (g1) →
C4: 0.04187337 | D4: 0.04687337 | E4: 0.05187337 | F4: 0.05687337 | G4: 0.06187337 | H4: 0.06687337 | I4: 0.07187337 | J4: 0.07687337 | K4: 0.08187337 | L4: 0.08687337 | M4: 0.09187337 | N4: 0.09687337 | O4: 0.10187337
B5: -0.00775 | C5: 45.098806 | D5: 45.984023 | E5: 46.884404 | F5: 47.800153 | G5: 48.731478 | H5: 49.678587 | I5: 50.641692 | J5: 51.621006 | K5: 52.616743 | L5: 53.629121 | M5: 54.658357 | N5: 55.704674 | O5: 56.768292
B6: -0.00275 | C6: 46.224417 | D6: 47.136904 | E6: 48.065081 | F6: 49.009159 | G6: 49.969354 | H6: 50.945883 | I6: 51.938964 | J6: 52.948819 | K6: 53.975669 | L6: 55.019741 | M6: 56.08126 | N6: 57.160455 | O6: 58.257558
B7: 0.00225 | C7: 47.441978 | D7: 48.383962 | E7: 49.342205 | F7: 50.316927 | G7: 51.308351 | H7: 52.316703 | I7: 53.342209 | J7: 54.385099 | K7: 55.445604 | L7: 56.523958 | M7: 57.620397 | N7: 58.735157 | O7: 59.868479
B8: 0.00725 | C8: 48.763234 | D8: 49.737229 | E8: 50.728099 | F8: 51.736074 | G8: 52.761387 | H8: 53.804271 | I8: 54.864964 | J8: 55.943703 | K8: 57.040729 | L8: 58.156286 | M8: 59.290618 | N8: 60.443972 | O8: 61.616598
B9: 0.01225 | C9: 50.202023 | D9: 51.210875 | E9: 52.237274 | F9: 53.281461 | G9: 54.343677 | H9: 55.424166 | I9: 56.523175 | J9: 57.640952 | K9: 58.777748 | L9: 59.933817 | M9: 61.109413 | N9: 62.304794 | O9: 63.520221
B10: 0.01725 | C10: 51.774758 | D10: 52.821711 | E10: 53.886948 | F10: 54.970717 | G10: 56.073271 | H10: 57.194866 | I10: 58.335758 | J10: 59.496208 | K10: 60.676476 | L10: 61.876828 | M10: 63.09753 | N10: 64.338851 | O10: 65.601063
A11: ↕ | B11: 0.02225 | C11: 53.501055 | D11: 54.589831 | E11: 55.697696 | F11: 56.824913 | G11: 57.971744 | H11: 59.138459 | I11: 60.325324 | J11: 61.532612 | K11: 62.760598 | L11: 64.009557 | M11: 65.279769 | N11: 66.571515 | O11: 67.88508
B12: 0.02725 | C12: 55.40456 | D12: 56.539452 | E12: 57.694322 | F12: 58.869446 | G12: 60.0651 | H12: 61.281565 | I12: 62.519123 | J12: 63.778058 | K12: 65.058659 | L12: 66.361215 | M12: 67.686019 | N12: 69.033367 | O12: 70.403556
B13: 0.03225 | C13: 57.514036 | D13: 58.700033 | E13: 59.906995 | F13: 61.13521 | G13: 62.38497 | H13: 63.656569 | I13: 64.950304 | J13: 66.266475 | K13: 67.605384 | L13: 68.967336 | M13: 70.35264 | N13: 71.761605 | O13: 73.194546
B14: 0.03725 | C14: 59.864825 | D14: 61.107774 | E14: 62.372786 | F14: 63.660166 | G14: 64.970221 | H14: 66.303261 | I14: 67.6596 | J14: 69.039554 | K14: 70.443441 | L14: 71.871585 | M14: 73.324309 | N14: 74.801941 | O14: 76.304812
B15: 0.04225 | C15: 62.500848 | D15: 63.807659 | E15: 65.137765 | F15: 66.491488 | G15: 67.869153 | H15: 69.27109 | I15: 70.697629 | J15: 72.149105 | K15: 73.625855 | L15: 75.128221 | M15: 76.656546 | N15: 78.211176 | O15: 79.792462
B16: 0.04725 | C16: 65.477371 | D16: 66.856293 | E16: 68.259901 | F16: 69.688537 | G16: 71.142546 | H16: 72.622279 | I16: 74.128085 | J16: 75.660322 | K16: 77.219347 | L16: 78.805522 | M16: 80.419213 | N16: 82.060788 | O16: 83.730618
B17: 0.05225 | C17: 68.864923 | D17: 70.325914 | E17: 71.813174 | F17: 73.327067 | G17: 74.867963 | H17: 76.436234 | I17: 78.032255 | J17: 79.656404 | K17: 81.309065 | L17: 82.990624 | M17: 84.701469 | N17: 86.441994 | O17: 88.212596
A20: TABLE 2: Intrinsic Value Sensitivity - High Growth Rate (g1) vs Cost of Equity (Ke)
A21: Approach 1 | g2 (stable) = 2.225% | Last Dividend = $4.95 | Base intrinsic value = $60.33
B22: g1 \ Ke | C22: ← COST OF EQUITY (Ke) →
C23: 0.09466634 | D23: 0.09966634 | E23: 0.10466634 | F23: 0.10966634 | G23: 0.11466634 | H23: 0.11966634 | I23: 0.12466634 | J23: 0.12966634 | K23: 0.13466634 | L23: 0.13966634 | M23: 0.14466634 | N23: 0.14966634 | O23: 0.15466634
B24: 0.04187337 | C24: 75.965937 | D24: 71.010583 | E24: 66.657305 | F24: 62.802775 | G24: 59.366025 | H24: 56.282711 | I24: 53.501053 | J24: 50.978915 | K24: 48.681655 | L24: 46.580535 | M24: 44.65151 | N24: 42.87431 | O24: 41.231728
B25: 0.04687337 | C25: 77.587791 | D25: 72.51432 | E25: 68.057482 | F25: 64.111445 | G25: 60.593281 | H25: 57.437086 | I25: 54.589829 | J25: 52.008351 | K25: 49.657174 | L25: 47.506862 | M25: 45.532789 | N25: 43.714195 | O25: 42.033455
B26: 0.05187337 | C26: 79.238887 | D26: 74.045043 | E26: 69.482669 | F26: 65.443382 | G26: 61.842255 | H26: 58.611795 | I26: 55.697694 | J26: 53.055753 | K26: 50.649638 | L26: 48.449205 | M26: 46.429235 | N26: 44.568467 | O26: 42.848852
B27: 0.05687337 | C27: 80.91963 | D27: 75.603126 | E27: 70.933213 | F27: 66.798908 | G27: 63.113246 | H27: 59.807118 | I27: 56.824911 | J27: 54.121366 | K27: 51.65928 | L27: 49.407783 | M27: 47.341054 | N27: 45.437322 | O27: 43.678105
B28: 0.06187337 | C28: 82.630431 | D28: 77.188947 | E28: 72.409463 | F28: 68.178347 | G28: 64.406558 | H28: 61.023336 | I28: 57.971743 | J28: 55.205438 | K28: 52.686331 | L28: 50.382816 | M28: 48.268454 | N28: 46.320955 | O28: 44.521399
B29: 0.06687337 | C29: 84.371706 | D29: 78.802888 | E29: 73.911772 | F29: 69.582026 | G29: 65.722494 | H29: 62.260735 | I29: 59.138457 | J29: 56.30822 | K29: 53.731028 | L29: 51.374525 | M29: 49.211644 | N29: 47.219567 | O29: 45.378923
B30: 0.07187337 | C30: 86.143872 | D30: 80.445333 | E30: 75.440496 | F30: 71.010276 | G30: 67.061363 | H30: 63.519601 | I30: 60.325322 | J30: 57.429964 | K30: 54.793608 | L30: 52.383135 | M30: 50.170837 | N30: 48.133358 | O30: 46.250867
B31: 0.07687337 | C31: 87.947352 | D31: 82.116673 | E31: 76.995995 | F31: 72.463431 | G31: 68.423474 | H31: 64.800226 | I31: 61.53261 | J31: 58.570925 | K31: 55.874312 | L31: 53.408872 | M31: 51.146246 | N31: 49.062528 | O31: 47.137423
B32: 0.08187337 | C32: 89.782571 | D32: 83.817298 | E32: 78.57863 | F32: 73.941827 | G32: 69.809142 | H32: 66.1029 | I32: 62.760596 | J32: 59.731361 | K32: 56.973382 | L32: 54.451965 | M32: 52.138088 | N32: 50.007284 | O32: 48.038783
B33: 0.08687337 | C33: 91.64996 | D33: 85.547604 | E33: 80.188769 | F33: 75.445803 | G33: 71.218683 | H33: 67.427921 | I33: 64.009555 | J33: 60.911532 | K33: 58.091061 | L33: 55.512643 | M33: 53.146578 | N33: 50.96783 | O33: 48.955144
B34: 0.09187337 | C34: 93.549952 | D34: 87.307992 | E34: 81.82678 | F34: 76.975703 | G34: 72.652415 | H34: 68.775586 | I34: 65.279767 | J34: 62.111698 | K34: 59.227597 | L34: 56.59114 | M34: 54.171938 | N34: 51.944375 | O34: 49.886702
B35: 0.09687337 | C35: 95.482986 | D35: 89.098864 | E35: 83.493036 | F35: 78.531872 | G35: 74.110661 | H35: 70.146195 | I35: 66.571513 | J35: 63.332125 | K35: 60.383239 | L35: 57.68769 | M35: 55.214389 | N35: 52.937127 | O35: 50.833656
B36: 0.10187337 | C36: 97.449502 | D36: 90.920626 | E36: 85.187913 | F36: 80.114659 | G36: 75.593746 | H36: 71.540052 | I36: 67.885077 | J36: 64.57308 | K36: 61.558236 | L36: 58.802529 | M36: 56.274153 | N36: 53.946299 | O36: 51.796207
A38: Legend: Green = Higher intrinsic value (more favourable) | Red = Lower intrinsic value (less favourable) | Blue highlighted = Base case assumption
A39: Note: Base case values - g1 = 7.19%, g2 = 2.225%, Ke (App 1) = 12.47%. All values represent intrinsic value per share ($AUD).
